{
  "version": "35.0.0",
  "files": {
    "4ed20fd726389e6333fd391eaf6097d7e44a62d73f7b7e098c4577fc98ecd98b": {
      "source": {
        "path": "CdkStack.template.json",
        "packaging": "file"
      },
      "destinations": {
        "current_account-current_region": {
          "bucketName": "cdk-hnb659fds-assets-${AWS::AccountId}-${AWS::Region}",
          "objectKey": "4ed20fd726389e6333fd391eaf6097d7e44a62d73f7b7e098c4577fc98ecd98b.json",
          "assumeRoleArn": "arn:${AWS::Partition}:iam::${AWS::AccountId}:role/cdk-hnb659fds-file-publishing-role-${AWS::AccountId}-${AWS::Region}"
        }
      }
    }
  },
  "dockerImages": {}
}